src/__init__.py
src/main.py
src/cli/__init__.py
src/cli/setup.py
src/cli/tool_topic.py
src/cli/tools/__init__.py
src/cli/tools/download.py
src/cli/tools/list.py
src/cli/tools/profiles.py
src/cli/tools/queue.py
src/cli/tools/upload.py
src/config/__init__.py
src/config/_cipher.py
src/config/profiles.py
src/config/store.py
src/config/version.py
src/tools/__init__.py
src/tools/files.py
src/tools/logging.py
src/tools/misc.py
src/tools/output.py
src/tools/pypi.py
src/tools/sb.py
src/tools/version.py
src/tools/service_bus/__init__.py
src/tools/service_bus/queue_info.py
tests/config/__init__.py
tests/config/test_cipher.py
tests/config/test_profiles.py
tests/config/test_store.py
tests/config/test_version.py
tests/tools/__init__.py
tests/tools/test_download.py
tests/tools/test_files.py
tests/tools/test_logging.py
tests/tools/test_misc.py
tests/tools/test_output.py
tests/tools/test_parse_connection.py
tests/tools/test_pypi.py
tests/tools/test_sb.py
tests/tools/test_version.py
sbcli_furlan-0.0.7.dist-info/LICENSE
sbcli_furlan-0.0.7.dist-info/METADATA
sbcli_furlan-0.0.7.dist-info/WHEEL
sbcli_furlan-0.0.7.dist-info/entry_points.txt
sbcli_furlan-0.0.7.dist-info/top_level.txt
sbcli_furlan-0.0.7.dist-info/zip-safe
sbcli_furlan-0.0.7.dist-info/RECORD
