Metadata-Version: 2.1
Name: sbcli-furlan
Version: 0.0.7
Summary: Azure Service Bus CLI
Home-page: https://github.com/guionardo/py-servicebus-cli
Author: Guionardo Furlan
Author-email: guionardo@gmail.com
License: MIT
Project-URL: Documentation, https://github.com/guionardo/py-servicebus-cli/wiki
Project-URL: Source, https://github.com/guionardo/py-servicebus-cli
Keywords: azure service bus
Platform: UNKNOWN
Classifier: Development Status :: 4 - Beta
Classifier: Environment :: Console
Classifier: Intended Audience :: Developers
Classifier: License :: OSI Approved :: MIT License
Classifier: Topic :: Software Development :: Build Tools
Classifier: Topic :: Utilities
Classifier: Programming Language :: Python
Classifier: Programming Language :: Python :: 3.8
Classifier: Programming Language :: Python :: 3.9
Requires-Python: >=3.8.*
License-File: LICENSE
Requires-Dist: azure-servicebus
Requires-Dist: xmltodict
Requires-Dist: cryptography
Requires-Dist: tqdm
